{
    "total_size": 3,
    "type_id": 3,
    "offset": 0,
    "products": [
        {
            "id": 1,
            "name": "Cafe French Vainilla",
            "description": "Si bien está inspirado en la tradición francesa, este envase de Breyers® aún conserva gran parte del orgullo estadounidense. Cada Breyers® French Vanilla contiene crema y leche 100 % de grado A, provenientes de vacas estadounidenses que no han sido tratadas con hormonas artificiales de crecimiento",
            "price": 24,
            "stars": 4,
            "img": "images/Coffe005.jpg",
            "location": "La Paz",
            "created_at": "2022-09",
            "update_at": "2022-09",
            "type_id": 1

        },
        {
            "id": 2,
            "name": "Café Almond Joe",
            "description": "Agregue sabor a nuez de chocolate y coco a su rutina matutina con Almond Joy Coffee. Un chorrito o dos de esta crema casera convierte tu ritual diario de café en un placer especial. Bebe y saborea en café caliente o helado.",
            "price": 24,
            "stars": 4,
            "img": "images/Coffe006.jpg",
            "location": "La Paz",
            "created_at": "2022-09",
            "update_at": "2022-09",
            "type_id": 2

        },
        {
            "id": 3,
            "name": "Café Expresso - El mejor",
            "description": "El café expreso es un tipo de café que contiene mayor cantidad de cafeína por volumen que la mayoría de los cafés, por eso se sirve en tazas pequeñas. No es que tenga más cafeína que el resto, sino que está concentrada en menor líquido. Un buen expreso es uno de los grandes placeres de la vida. No hay nada como ese momento de paz cuando estás desayunando y disfrutas del aroma del café ",
            "price": 10,
            "stars": 4,
            "img": "images/Coffe007.jpg",
            "location": "La Paz",
            "created_at": "2022-09",
            "update_at": "2022-09",
            "type_id": 3

        }
    ]

}